{
  "opening_id": "1",
  "line_order": [
    437,
    574,
    108,
    492,
    103,
    377,
    215,
    221,
    131,
    115,
    96,
    326,
    259,
    157,
    365,
    101,
    315,
    385,
    182,
    290,
    559,
    591,
    430,
    67,
    66,
    16,
    124,
    49,
    199,
    250,
    489,
    370,
    238,
    34,
    580,
    346,
    133,
    361,
    533,
    307,
    146,
    510,
    286,
    88,
    106,
    207,
    171,
    154,
    204,
    457,
    442,
    255,
    292,
    42,
    116,
    163,
    170,
    318,
    367,
    504,
    420,
    525,
    476,
    188,
    33,
    311,
    381,
    305,
    419,
    142,
    119,
    342,
    5,
    231,
    122,
    256,
    458,
    71,
    45,
    123,
    558,
    502,
    15,
    248,
    529,
    92,
    487,
    185,
    354,
    386,
    364,
    180,
    229,
    26,
    237,
    478,
    179,
    94,
    428,
    373,
    345,
    588,
    57,
    4,
    586,
    236,
    12,
    571,
    503,
    293,
    445,
    228,
    398,
    539,
    54,
    355,
    234,
    196,
    448,
    520,
    314,
    242,
    212,
    75,
    76,
    25,
    449,
    291,
    0,
    444,
    69,
    453,
    544,
    135,
    23,
    541,
    246,
    450,
    262,
    384,
    82,
    412,
    301,
    583,
    32,
    11,
    483,
    7,
    538,
    351,
    585,
    79,
    208,
    62,
    514,
    548,
    200,
    243,
    65,
    162,
    431,
    422,
    375,
    189,
    168,
    509,
    358,
    306,
    576,
    121,
    550,
    447,
    144,
    156,
    482,
    549,
    410,
    415,
    73,
    302,
    452,
    547,
    553,
    72,
    460,
    289,
    322,
    432,
    522,
    417,
    374,
    513,
    134,
    143,
    277,
    296,
    132,
    480,
    459,
    30,
    85,
    496,
    251,
    220,
    28,
    138,
    555,
    455,
    528,
    161,
    22,
    150,
    240,
    197,
    20,
    534,
    383,
    59,
    109,
    577,
    421,
    268,
    424,
    205,
    321,
    317,
    357,
    14,
    414,
    158,
    29,
    397,
    202,
    498,
    267,
    294,
    543,
    280,
    466,
    209,
    337,
    298,
    13,
    393,
    9,
    24,
    227,
    58,
    112,
    194,
    331,
    2,
    468,
    335,
    258,
    540,
    98,
    407,
    210,
    10,
    380,
    327,
    441,
    56,
    334,
    102,
    587,
    554,
    436,
    41,
    17,
    55,
    39,
    31,
    435,
    247,
    408,
    477,
    264,
    8,
    295,
    349,
    165,
    319,
    369,
    176,
    282,
    224,
    425,
    19,
    149,
    557,
    454,
    147,
    270,
    97,
    389,
    239,
    382,
    297,
    36,
    565,
    48,
    309,
    61,
    325,
    531,
    271,
    426,
    265,
    310,
    89,
    253,
    581,
    475,
    356,
    546,
    60,
    47,
    474,
    470,
    320,
    81,
    113,
    433,
    396,
    416,
    213,
    451,
    507,
    573,
    567,
    400,
    561,
    40,
    434,
    582,
    43,
    118,
    50,
    114,
    532,
    390,
    440,
    287,
    266,
    387,
    488,
    279,
    308,
    391,
    584,
    590,
    111,
    473,
    485,
    125,
    411,
    217,
    392,
    190,
    278,
    93,
    579,
    446,
    219,
    232,
    211,
    304,
    139,
    379,
    100,
    512,
    245,
    6,
    530,
    254,
    439,
    78,
    526,
    536,
    225,
    52,
    572,
    535,
    27,
    404,
    497,
    77,
    527,
    261,
    467,
    152,
    84,
    545,
    409,
    99,
    465,
    328,
    316,
    3,
    360,
    461,
    223,
    500,
    53,
    148,
    1,
    164,
    284,
    333,
    348,
    230,
    44,
    372,
    427,
    542,
    51,
    332,
    68,
    281,
    472,
    570,
    117,
    463,
    177,
    218,
    70,
    275,
    341,
    378,
    388,
    136,
    137,
    169,
    491,
    402,
    274,
    438,
    272,
    518,
    343,
    173,
    350,
    347,
    494,
    340,
    276,
    104,
    363,
    505,
    273,
    110,
    80,
    508,
    37,
    269,
    128,
    186,
    203,
    481,
    352,
    153,
    329,
    456,
    523,
    145,
    140,
    241,
    344,
    499,
    252,
    249,
    201,
    263,
    216,
    353,
    368,
    399,
    129,
    285,
    371,
    493,
    564,
    394,
    18,
    401,
    260,
    462,
    560,
    556,
    83,
    184,
    405,
    515,
    191,
    21,
    464,
    486,
    244,
    35,
    63,
    222,
    443,
    313,
    578,
    552,
    86,
    155,
    90,
    395,
    235,
    589,
    226,
    178,
    195,
    95,
    193,
    563,
    406,
    87,
    429,
    592,
    206,
    181,
    566,
    74,
    323,
    519,
    288,
    471,
    501,
    516,
    569,
    506,
    167,
    214,
    127,
    303,
    172,
    418,
    283,
    495,
    339,
    330,
    120,
    192,
    338,
    141,
    517,
    183,
    562,
    159,
    336,
    299,
    151,
    38,
    551,
    359,
    198,
    511,
    568,
    575,
    479,
    376,
    126,
    64,
    91,
    175,
    521,
    105,
    484,
    312,
    537,
    403,
    413,
    187,
    362,
    160,
    174,
    107,
    257,
    469,
    524,
    130,
    423,
    324,
    166,
    490,
    46,
    366,
    300,
    233
  ],
  "current_line_ptr": 0,
  "ply_index": 4,
  "mistakes": []
}